CHANGES.txt
LICENSE
MANIFEST.in
README.md
setup.py
bin/wiotp-cli
src/ibmiotf/__init__.py
src/ibmiotf/application.py
src/ibmiotf/device.py
src/ibmiotf/gateway.py
src/ibmiotf/messaging.pem
src/ibmiotf.egg-info/PKG-INFO
src/ibmiotf.egg-info/SOURCES.txt
src/ibmiotf.egg-info/dependency_links.txt
src/ibmiotf.egg-info/requires.txt
src/ibmiotf.egg-info/top_level.txt
src/ibmiotf/api/__init__.py
src/ibmiotf/api/common.py
src/ibmiotf/api/lec/__init__.py
src/ibmiotf/api/registry/__init__.py
src/ibmiotf/api/registry/devices.py
src/ibmiotf/api/registry/types.py
src/ibmiotf/api/status/__init__.py
src/ibmiotf/api/usage/__init__.py
src/ibmiotf/codecs/__init__.py
test/test_api_lec.py
test/test_api_registry_devices.py
test/test_api_registry_devicetypes.py
test/test_api_status.py
test/test_api_usage.py
test/test_codecs.py
test/test_device.py
test/test_device_http.py
test/test_device_mgd.py
test/test_gateway.py
test/test_gateway_mgd.py