Metadata-Version: 1.1
Name: ibmiotf
Version: 0.4.0
Summary: Python Client for IBM Watson IoT Platform
Home-page: https://github.com/ibm-watson-iot/iot-python
Author: David Parker
Author-email: parkerda@uk.ibm.com
License: Eclipse Public License - v 1.0
